aws_lambda/__init__.py
aws_lambda/__version__.py
aws_lambda/apig/__init__.py
mutton/__init__.py
mutton/__version__.py
mutton/apig/__init__.py
mutton-0.0.5.dist-info/METADATA
mutton-0.0.5.dist-info/RECORD
mutton-0.0.5.dist-info/WHEEL
mutton-0.0.5.dist-info/top_level.txt
pal/__init__.py
pal/__version__.py
pal/apig/__init__.py
